[
  {
    "id": "58bd1b02-6082-42e1-83c8-505b416a08a6",
    "createdBy": "ba73aa73-367c-4bca-9dad-4b5866420d3c",
    "created": "1552253389743",
    "updated": "1541310985154",
    "type": "zb",
    "fields": {
      "name": "Low Zuni Bowl",
      "quantity": [
        11,
        2
      ],
      "orientation": "streamwise",
      "position": "sideChannel",
      "obstruction": "deformable",
      "stage": "typicalFlood",
      "notes": "Fugiat in rerum eaque labore explicabo voluptatum voluptatem error. Aut asperiores ea id voluptatem veniam necessitatibus qui et. Doloribus distinctio dolorem. Cum inventore nam quo officiis et mollitia. Minima qui eos minima vitae neque perspiciatis consequatur recusandae."
    },
    "geoJSON": {
      "type": "Feature",
      "properties": {
        "type": "dot"
      },
      "geometry": {
        "type": "Point",
        "coordinates": [
          -122.57048554811618,
          49.26123495709179
        ]
      }
    }
  },
  {
    "id": "1157b75a-b1c5-47a9-9ae0-d8d2698b69d9",
    "createdBy": "d3f71097-ac5a-4db9-b9a8-92319276cdf6",
    "created": "1534293546223",
    "updated": "1544291682322",
    "type": "zb",
    "geoJSON": {
      "type": "Feature",
      "properties": {
        "type": "dot"
      },
      "geometry": {
        "type": "Point",
        "coordinates": [
          -122.57048554811618,
          49.26123495709179
        ]
      }
    },
    "meta": {
      "source": "58bd1b02-6082-42e1-83c8-505b416a08a6"
    },
    "fields": {
      "name": "Low Zuni Bowl",
      "quantity": [
        11,
        2
      ],
      "orientation": "streamwise",
      "position": "sideChannel",
      "obstruction": "deformable",
      "stage": "typicalFlood",
      "notes": "Fugiat in rerum eaque labore explicabo voluptatum voluptatem error. Aut asperiores ea id voluptatem veniam necessitatibus qui et. Doloribus distinctio dolorem. Cum inventore nam quo officiis et mollitia. Minima qui eos minima vitae neque perspiciatis consequatur recusandae."
    }
  }
]